binaryrain_helper_cloud_dataverse/__init__.py
binaryrain_helper_cloud_dataverse/dataverse.py
binaryrain_helper_cloud_dataverse-0.0.2.dist-info/METADATA
binaryrain_helper_cloud_dataverse-0.0.2.dist-info/WHEEL
binaryrain_helper_cloud_dataverse-0.0.2.dist-info/top_level.txt
binaryrain_helper_cloud_dataverse-0.0.2.dist-info/RECORD
