Metadata-Version: 2.4
Name: binaryrain-helper-cloud-dataverse
Version: 0.0.2
Summary: Aims to simplify and help with connecting to and using Microsoft Dataverse.
Author: Binary Rain, Marcel T.O
Project-URL: Homepage, https://binaryrain-net.github.io/Binary-Rain-Helper-Toolkit/
Keywords: binary rain,common,help,functions,azure
Classifier: Programming Language :: Python
Classifier: Programming Language :: Python :: 3
Requires-Python: >=3.10
Requires-Dist: requests>=2.32.5
